{"nodes": [{"id": "10", "group": "None", "label": "10"}, {"id": "180", "group": "None", "label": "180"}, {"id": "15", "group": "None", "label": "15"}, {"id": "21", "group": "None", "label": "21"}, {"id": "151", "group": "None", "label": "151"}, {"id": "0", "group": "None", "label": "0"}, {"id": "28", "group": "None", "label": "28"}, {"id": "102", "group": "None", "label": "102"}, {"id": "92", "group": "None", "label": "92"}, {"id": "41", "group": "None", "label": "41"}, {"id": "64", "group": "None", "label": "64"}, {"id": "36", "group": "None", "label": "36"}, {"id": "68", "group": "None", "label": "68"}, {"id": "77", "group": "None", "label": "77"}, {"id": "7", "group": "None", "label": "7"}, {"id": "48", "group": "None", "label": "48"}, {"id": "176", "group": "None", "label": "176"}, {"id": "161", "group": "None", "label": "161"}, {"id": "141", "group": "None", "label": "141"}, {"id": "3", "group": "None", "label": "3"}, {"id": "174", "group": "None", "label": "174"}, {"id": "123", "group": "None", "label": "123"}, {"id": "16", "group": "None", "label": "16"}, {"id": "150", "group": "None", "label": "150"}, {"id": "179", "group": "None", "label": "179"}, {"id": "4", "group": "None", "label": "4"}, {"id": "53", "group": "None", "label": "53"}, {"id": "11", "group": "None", "label": "11"}, {"id": "72", "group": "None", "label": "72"}, {"id": "62", "group": "None", "label": "62"}, {"id": "85", "group": "None", "label": "85"}, {"id": "182", "group": "None", "label": "182"}, {"id": "57", "group": "None", "label": "57"}, {"id": "112", "group": "None", "label": "112"}, {"id": "137", "group": "None", "label": "137"}, {"id": "131", "group": "None", "label": "131"}, {"id": "121", "group": "None", "label": "121"}, {"id": "135", "group": "None", "label": "135"}, {"id": "144", "group": "None", "label": "144"}, {"id": "93", "group": "None", "label": "93"}, {"id": "25", "group": "None", "label": "25"}, {"id": "143", "group": "None", "label": "143"}, {"id": "110", "group": "None", "label": "110"}, {"id": "35", "group": "None", "label": "35"}, {"id": "55", "group": "None", "label": "55"}, {"id": "152", "group": "None", "label": "152"}, {"id": "45", "group": "None", "label": "45"}, {"id": "5", "group": "None", "label": "5"}, {"id": "43", "group": "None", "label": "43"}, {"id": "27", "group": "None", "label": "27"}, {"id": "56", "group": "None", "label": "56"}, {"id": "40", "group": "None", "label": "40"}, {"id": "91", "group": "None", "label": "91"}, {"id": "105", "group": "None", "label": "105"}, {"id": "95", "group": "None", "label": "95"}, {"id": "114", "group": "None", "label": "114"}, {"id": "120", "group": "None", "label": "120"}, {"id": "104", "group": "None", "label": "104"}, {"id": "166", "group": "None", "label": "166"}, {"id": "127", "group": "None", "label": "127"}, {"id": "181", "group": "None", "label": "181"}, {"id": "86", "group": "None", "label": "86"}, {"id": "115", "group": "None", "label": "115"}, {"id": "99", "group": "None", "label": "99"}, {"id": "23", "group": "None", "label": "23"}, {"id": "84", "group": "None", "label": "84"}, {"id": "154", "group": "None", "label": "154"}, {"id": "173", "group": "None", "label": "173"}, {"id": "20", "group": "None", "label": "20"}, {"id": "54", "group": "None", "label": "54"}, {"id": "126", "group": "None", "label": "126"}, {"id": "38", "group": "None", "label": "38"}, {"id": "58", "group": "None", "label": "58"}, {"id": "51", "group": "None", "label": "51"}, {"id": "26", "group": "None", "label": "26"}, {"id": "39", "group": "None", "label": "39"}, {"id": "100", "group": "None", "label": "100"}, {"id": "107", "group": "None", "label": "107"}, {"id": "113", "group": "None", "label": "113"}, {"id": "175", "group": "None", "label": "175"}, {"id": "97", "group": "None", "label": "97"}, {"id": "172", "group": "None", "label": "172"}, {"id": "156", "group": "None", "label": "156"}, {"id": "183", "group": "None", "label": "183"}, {"id": "47", "group": "None", "label": "47"}, {"id": "119", "group": "None", "label": "119"}, {"id": "171", "group": "None", "label": "171"}, {"id": "37", "group": "None", "label": "37"}, {"id": "19", "group": "None", "label": "19"}, {"id": "184", "group": "None", "label": "184"}, {"id": "9", "group": "None", "label": "9"}, {"id": "32", "group": "None", "label": "32"}, {"id": "83", "group": "None", "label": "83"}, {"id": "67", "group": "None", "label": "67"}, {"id": "106", "group": "None", "label": "106"}, {"id": "133", "group": "None", "label": "133"}, {"id": "96", "group": "None", "label": "96"}, {"id": "90", "group": "None", "label": "90"}, {"id": "78", "group": "None", "label": "78"}, {"id": "142", "group": "None", "label": "142"}, {"id": "167", "group": "None", "label": "167"}, {"id": "136", "group": "None", "label": "136"}, {"id": "140", "group": "None", "label": "140"}, {"id": "165", "group": "None", "label": "165"}, {"id": "124", "group": "None", "label": "124"}, {"id": "17", "group": "None", "label": "17"}, {"id": "149", "group": "None", "label": "149"}, {"id": "1", "group": "None", "label": "1"}, {"id": "30", "group": "None", "label": "30"}, {"id": "164", "group": "None", "label": "164"}, {"id": "2", "group": "None", "label": "2"}, {"id": "76", "group": "None", "label": "76"}, {"id": "60", "group": "None", "label": "60"}, {"id": "66", "group": "None", "label": "66"}, {"id": "89", "group": "None", "label": "89"}, {"id": "73", "group": "None", "label": "73"}, {"id": "61", "group": "None", "label": "61"}, {"id": "65", "group": "None", "label": "65"}, {"id": "162", "group": "None", "label": "162"}, {"id": "125", "group": "None", "label": "125"}, {"id": "148", "group": "None", "label": "148"}, {"id": "132", "group": "None", "label": "132"}, {"id": "74", "group": "None", "label": "74"}, {"id": "13", "group": "None", "label": "13"}, {"id": "87", "group": "None", "label": "87"}, {"id": "178", "group": "None", "label": "178"}, {"id": "46", "group": "None", "label": "46"}, {"id": "69", "group": "None", "label": "69"}, {"id": "34", "group": "None", "label": "34"}, {"id": "59", "group": "None", "label": "59"}, {"id": "49", "group": "None", "label": "49"}, {"id": "82", "group": "None", "label": "82"}, {"id": "117", "group": "None", "label": "117"}, {"id": "31", "group": "None", "label": "31"}, {"id": "146", "group": "None", "label": "146"}, {"id": "44", "group": "None", "label": "44"}, {"id": "109", "group": "None", "label": "109"}, {"id": "128", "group": "None", "label": "128"}, {"id": "155", "group": "None", "label": "155"}, {"id": "118", "group": "None", "label": "118"}, {"id": "145", "group": "None", "label": "145"}, {"id": "108", "group": "None", "label": "108"}, {"id": "168", "group": "None", "label": "168"}, {"id": "158", "group": "None", "label": "158"}, {"id": "6", "group": "None", "label": "6"}, {"id": "103", "group": "None", "label": "103"}, {"id": "80", "group": "None", "label": "80"}, {"id": "177", "group": "None", "label": "177"}, {"id": "70", "group": "None", "label": "70"}, {"id": "29", "group": "None", "label": "29"}, {"id": "18", "group": "None", "label": "18"}, {"id": "52", "group": "None", "label": "52"}, {"id": "42", "group": "None", "label": "42"}, {"id": "116", "group": "None", "label": "116"}, {"id": "14", "group": "None", "label": "14"}, {"id": "139", "group": "None", "label": "139"}, {"id": "79", "group": "None", "label": "79"}, {"id": "98", "group": "None", "label": "98"}, {"id": "129", "group": "None", "label": "129"}, {"id": "88", "group": "None", "label": "88"}, {"id": "111", "group": "None", "label": "111"}, {"id": "138", "group": "None", "label": "138"}, {"id": "101", "group": "None", "label": "101"}, {"id": "8", "group": "None", "label": "8"}, {"id": "163", "group": "None", "label": "163"}, {"id": "157", "group": "None", "label": "157"}, {"id": "50", "group": "None", "label": "50"}, {"id": "147", "group": "None", "label": "147"}, {"id": "170", "group": "None", "label": "170"}, {"id": "63", "group": "None", "label": "63"}, {"id": "160", "group": "None", "label": "160"}, {"id": "22", "group": "None", "label": "22"}, {"id": "12", "group": "None", "label": "12"}, {"id": "169", "group": "None", "label": "169"}, {"id": "122", "group": "None", "label": "122"}, {"id": "81", "group": "None", "label": "81"}, {"id": "71", "group": "None", "label": "71"}, {"id": "75", "group": "None", "label": "75"}, {"id": "94", "group": "None", "label": "94"}, {"id": "159", "group": "None", "label": "159"}, {"id": "24", "group": "None", "label": "24"}, {"id": "33", "group": "None", "label": "33"}, {"id": "130", "group": "None", "label": "130"}, {"id": "134", "group": "None", "label": "134"}, {"id": "153", "group": "None", "label": "153"}], "edges": [{"source": "10", "target": "180", "id": 0, "weight": "1", "group": "aamaadmiparty"}, {"source": "10", "target": "15", "id": 1, "weight": "1", "group": "aamaadmiparty"}, {"source": "10", "target": "21", "id": 2, "weight": "1", "group": "aamaadmiparty"}, {"source": "10", "target": "28", "id": 3, "weight": "1", "group": "aamaadmiparty"}, {"source": "10", "target": "102", "id": 4, "weight": "1", "group": "aamaadmiparty"}, {"source": "10", "target": "92", "id": 5, "weight": "1", "group": "aamaadmiparty"}, {"source": "10", "target": "41", "id": 6, "weight": "1", "group": "aamaadmiparty"}, {"source": "10", "target": "64", "id": 7, "weight": "1", "group": "aamaadmiparty"}, {"source": "10", "target": "77", "id": 8, "weight": "1", "group": "aamaadmiparty"}, {"source": "10", "target": "161", "id": 9, "weight": "1", "group": "aamaadmiparty"}, {"source": "10", "target": "141", "id": 10, "weight": "1", "group": "aamaadmiparty"}, {"source": "10", "target": "3", "id": 11, "weight": "1", "group": "aamaadmiparty"}, {"source": "10", "target": "174", "id": 12, "weight": "1", "group": "aamaadmiparty"}, {"source": "10", "target": "123", "id": 13, "weight": "1", "group": "aamaadmiparty"}, {"source": "10", "target": "16", "id": 14, "weight": "1", "group": "aamaadmiparty"}, {"source": "10", "target": "150", "id": 15, "weight": "1", "group": "aamaadmiparty"}, {"source": "10", "target": "179", "id": 16, "weight": "1", "group": "aamaadmiparty"}, {"source": "10", "target": "4", "id": 17, "weight": "1", "group": "aamaadmiparty"}, {"source": "10", "target": "11", "id": 18, "weight": "1", "group": "aamaadmiparty"}, {"source": "10", "target": "72", "id": 19, "weight": "1", "group": "aamaadmiparty"}, {"source": "10", "target": "62", "id": 20, "weight": "1", "group": "aamaadmiparty"}, {"source": "10", "target": "85", "id": 21, "weight": "1", "group": "aamaadmiparty"}, {"source": "10", "target": "182", "id": 22, "weight": "1", "group": "aamaadmiparty"}, {"source": "10", "target": "57", "id": 23, "weight": "1", "group": "aamaadmiparty"}, {"source": "10", "target": "137", "id": 24, "weight": "1", "group": "aamaadmiparty"}, {"source": "10", "target": "131", "id": 25, "weight": "1", "group": "aamaadmiparty"}, {"source": "10", "target": "121", "id": 26, "weight": "1", "group": "aamaadmiparty"}, {"source": "10", "target": "144", "id": 27, "weight": "1", "group": "aamaadmiparty"}, {"source": "10", "target": "93", "id": 28, "weight": "1", "group": "aamaadmiparty"}, {"source": "10", "target": "25", "id": 29, "weight": "1", "group": "aamaadmiparty"}, {"source": "10", "target": "143", "id": 30, "weight": "1", "group": "aamaadmiparty"}, {"source": "10", "target": "55", "id": 31, "weight": "1", "group": "aamaadmiparty"}, {"source": "10", "target": "152", "id": 32, "weight": "1", "group": "aamaadmiparty"}, {"source": "10", "target": "45", "id": 33, "weight": "1", "group": "aamaadmiparty"}, {"source": "10", "target": "68", "id": 34, "weight": "1", "group": "aamaadmiparty"}, {"source": "10", "target": "43", "id": 35, "weight": "1", "group": "aamaadmiparty"}, {"source": "10", "target": "27", "id": 36, "weight": "1", "group": "aamaadmiparty"}, {"source": "10", "target": "56", "id": 37, "weight": "1", "group": "aamaadmiparty"}, {"source": "10", "target": "40", "id": 38, "weight": "1", "group": "aamaadmiparty"}, {"source": "10", "target": "91", "id": 39, "weight": "1", "group": "aamaadmiparty"}, {"source": "10", "target": "114", "id": 40, "weight": "1", "group": "aamaadmiparty"}, {"source": "10", "target": "120", "id": 41, "weight": "1", "group": "aamaadmiparty"}, {"source": "10", "target": "104", "id": 42, "weight": "1", "group": "aamaadmiparty"}, {"source": "10", "target": "127", "id": 43, "weight": "1", "group": "aamaadmiparty"}, {"source": "10", "target": "86", "id": 44, "weight": "1", "group": "aamaadmiparty"}, {"source": "10", "target": "115", "id": 45, "weight": "1", "group": "aamaadmiparty"}, {"source": "10", "target": "99", "id": 46, "weight": "1", "group": "aamaadmiparty"}, {"source": "10", "target": "173", "id": 47, "weight": "1", "group": "aamaadmiparty"}, {"source": "10", "target": "54", "id": 48, "weight": "1", "group": "aamaadmiparty"}, {"source": "10", "target": "38", "id": 49, "weight": "1", "group": "aamaadmiparty"}, {"source": "10", "target": "51", "id": 50, "weight": "1", "group": "aamaadmiparty"}, {"source": "10", "target": "26", "id": 51, "weight": "1", "group": "aamaadmiparty"}, {"source": "10", "target": "39", "id": 52, "weight": "1", "group": "aamaadmiparty"}, {"source": "10", "target": "100", "id": 53, "weight": "1", "group": "aamaadmiparty"}, {"source": "10", "target": "107", "id": 54, "weight": "1", "group": "aamaadmiparty"}, {"source": "10", "target": "113", "id": 55, "weight": "1", "group": "aamaadmiparty"}, {"source": "10", "target": "97", "id": 56, "weight": "1", "group": "aamaadmiparty"}, {"source": "10", "target": "172", "id": 57, "weight": "1", "group": "aamaadmiparty"}, {"source": "10", "target": "156", "id": 58, "weight": "1", "group": "aamaadmiparty"}, {"source": "10", "target": "183", "id": 59, "weight": "1", "group": "aamaadmiparty"}, {"source": "10", "target": "47", "id": 60, "weight": "1", "group": "aamaadmiparty"}, {"source": "10", "target": "171", "id": 61, "weight": "1", "group": "aamaadmiparty"}, {"source": "10", "target": "37", "id": 62, "weight": "1", "group": "aamaadmiparty"}, {"source": "10", "target": "19", "id": 63, "weight": "1", "group": "aamaadmiparty"}, {"source": "10", "target": "184", "id": 64, "weight": "1", "group": "aamaadmiparty"}, {"source": "10", "target": "9", "id": 65, "weight": "1", "group": "aamaadmiparty"}, {"source": "10", "target": "32", "id": 66, "weight": "1", "group": "aamaadmiparty"}, {"source": "10", "target": "83", "id": 67, "weight": "1", "group": "aamaadmiparty"}, {"source": "10", "target": "67", "id": 68, "weight": "1", "group": "aamaadmiparty"}, {"source": "10", "target": "106", "id": 69, "weight": "1", "group": "aamaadmiparty"}, {"source": "10", "target": "133", "id": 70, "weight": "1", "group": "aamaadmiparty"}, {"source": "10", "target": "96", "id": 71, "weight": "1", "group": "aamaadmiparty"}, {"source": "10", "target": "90", "id": 72, "weight": "1", "group": "aamaadmiparty"}, {"source": "10", "target": "78", "id": 73, "weight": "1", "group": "aamaadmiparty"}, {"source": "10", "target": "142", "id": 74, "weight": "1", "group": "aamaadmiparty"}, {"source": "10", "target": "167", "id": 75, "weight": "1", "group": "aamaadmiparty"}, {"source": "10", "target": "136", "id": 76, "weight": "1", "group": "aamaadmiparty"}, {"source": "10", "target": "165", "id": 77, "weight": "1", "group": "aamaadmiparty"}, {"source": "10", "target": "58", "id": 78, "weight": "1", "group": "aamaadmiparty"}, {"source": "10", "target": "124", "id": 79, "weight": "1", "group": "aamaadmiparty"}, {"source": "10", "target": "17", "id": 80, "weight": "1", "group": "aamaadmiparty"}, {"source": "10", "target": "149", "id": 81, "weight": "1", "group": "aamaadmiparty"}, {"source": "10", "target": "1", "id": 82, "weight": "1", "group": "aamaadmiparty"}, {"source": "10", "target": "30", "id": 83, "weight": "1", "group": "aamaadmiparty"}, {"source": "10", "target": "164", "id": 84, "weight": "1", "group": "aamaadmiparty"}, {"source": "10", "target": "2", "id": 85, "weight": "1", "group": "aamaadmiparty"}, {"source": "10", "target": "76", "id": 86, "weight": "1", "group": "aamaadmiparty"}, {"source": "10", "target": "60", "id": 87, "weight": "1", "group": "aamaadmiparty"}, {"source": "10", "target": "66", "id": 88, "weight": "1", "group": "aamaadmiparty"}, {"source": "10", "target": "89", "id": 89, "weight": "1", "group": "aamaadmiparty"}, {"source": "10", "target": "73", "id": 90, "weight": "1", "group": "aamaadmiparty"}, {"source": "10", "target": "61", "id": 91, "weight": "1", "group": "aamaadmiparty"}, {"source": "10", "target": "65", "id": 92, "weight": "2", "group": "aamaadmiparty"}, {"source": "10", "target": "162", "id": 93, "weight": "1", "group": "aamaadmiparty"}, {"source": "10", "target": "125", "id": 94, "weight": "1", "group": "aamaadmiparty"}, {"source": "10", "target": "148", "id": 95, "weight": "1", "group": "aamaadmiparty"}, {"source": "10", "target": "132", "id": 96, "weight": "1", "group": "aamaadmiparty"}, {"source": "10", "target": "74", "id": 97, "weight": "1", "group": "aamaadmiparty"}, {"source": "10", "target": "13", "id": 98, "weight": "1", "group": "aamaadmiparty"}, {"source": "10", "target": "87", "id": 99, "weight": "1", "group": "aamaadmiparty"}, {"source": "10", "target": "178", "id": 100, "weight": "1", "group": "aamaadmiparty"}, {"source": "10", "target": "46", "id": 101, "weight": "1", "group": "aamaadmiparty"}, {"source": "10", "target": "69", "id": 102, "weight": "1", "group": "aamaadmiparty"}, {"source": "10", "target": "59", "id": 103, "weight": "1", "group": "aamaadmiparty"}, {"source": "10", "target": "49", "id": 104, "weight": "1", "group": "aamaadmiparty"}, {"source": "10", "target": "82", "id": 105, "weight": "1", "group": "aamaadmiparty"}, {"source": "10", "target": "117", "id": 106, "weight": "1", "group": "aamaadmiparty"}, {"source": "10", "target": "31", "id": 107, "weight": "1", "group": "aamaadmiparty"}, {"source": "10", "target": "146", "id": 108, "weight": "1", "group": "aamaadmiparty"}, {"source": "10", "target": "44", "id": 109, "weight": "1", "group": "aamaadmiparty"}, {"source": "10", "target": "128", "id": 110, "weight": "1", "group": "aamaadmiparty"}, {"source": "10", "target": "155", "id": 111, "weight": "1", "group": "aamaadmiparty"}, {"source": "10", "target": "118", "id": 112, "weight": "1", "group": "aamaadmiparty"}, {"source": "10", "target": "145", "id": 113, "weight": "1", "group": "aamaadmiparty"}, {"source": "10", "target": "108", "id": 114, "weight": "1", "group": "aamaadmiparty"}, {"source": "10", "target": "168", "id": 115, "weight": "1", "group": "aamaadmiparty"}, {"source": "10", "target": "158", "id": 116, "weight": "1", "group": "aamaadmiparty"}, {"source": "10", "target": "6", "id": 117, "weight": "1", "group": "aamaadmiparty"}, {"source": "10", "target": "103", "id": 118, "weight": "1", "group": "aamaadmiparty"}, {"source": "10", "target": "80", "id": 119, "weight": "1", "group": "aamaadmiparty"}, {"source": "10", "target": "177", "id": 120, "weight": "1", "group": "aamaadmiparty"}, {"source": "10", "target": "70", "id": 121, "weight": "1", "group": "aamaadmiparty"}, {"source": "10", "target": "29", "id": 122, "weight": "1", "group": "aamaadmiparty"}, {"source": "10", "target": "52", "id": 123, "weight": "1", "group": "aamaadmiparty"}, {"source": "10", "target": "42", "id": 124, "weight": "1", "group": "aamaadmiparty"}, {"source": "10", "target": "116", "id": 125, "weight": "1", "group": "aamaadmiparty"}, {"source": "10", "target": "14", "id": 126, "weight": "1", "group": "aamaadmiparty"}, {"source": "10", "target": "139", "id": 127, "weight": "1", "group": "aamaadmiparty"}, {"source": "10", "target": "98", "id": 128, "weight": "1", "group": "aamaadmiparty"}, {"source": "10", "target": "129", "id": 129, "weight": "1", "group": "aamaadmiparty"}, {"source": "10", "target": "88", "id": 130, "weight": "1", "group": "aamaadmiparty"}, {"source": "10", "target": "111", "id": 131, "weight": "1", "group": "aamaadmiparty"}, {"source": "10", "target": "138", "id": 132, "weight": "1", "group": "aamaadmiparty"}, {"source": "10", "target": "101", "id": 133, "weight": "1", "group": "aamaadmiparty"}, {"source": "10", "target": "8", "id": 134, "weight": "2", "group": "aamaadmiparty"}, {"source": "10", "target": "157", "id": 135, "weight": "1", "group": "aamaadmiparty"}, {"source": "10", "target": "50", "id": 136, "weight": "1", "group": "aamaadmiparty"}, {"source": "10", "target": "147", "id": 137, "weight": "1", "group": "aamaadmiparty"}, {"source": "10", "target": "170", "id": 138, "weight": "1", "group": "aamaadmiparty"}, {"source": "10", "target": "63", "id": 139, "weight": "1", "group": "aamaadmiparty"}, {"source": "10", "target": "160", "id": 140, "weight": "1", "group": "aamaadmiparty"}, {"source": "10", "target": "22", "id": 141, "weight": "1", "group": "aamaadmiparty"}, {"source": "10", "target": "12", "id": 142, "weight": "1", "group": "aamaadmiparty"}, {"source": "10", "target": "169", "id": 143, "weight": "1", "group": "aamaadmiparty"}, {"source": "10", "target": "122", "id": 144, "weight": "1", "group": "aamaadmiparty"}, {"source": "10", "target": "81", "id": 145, "weight": "1", "group": "aamaadmiparty"}, {"source": "10", "target": "71", "id": 146, "weight": "1", "group": "aamaadmiparty"}, {"source": "10", "target": "94", "id": 147, "weight": "1", "group": "aamaadmiparty"}, {"source": "10", "target": "33", "id": 148, "weight": "1", "group": "aamaadmiparty"}, {"source": "10", "target": "130", "id": 149, "weight": "1", "group": "aamaadmiparty"}, {"source": "10", "target": "153", "id": 150, "weight": "1", "group": "aamaadmiparty"}, {"source": "151", "target": "0", "id": 151, "weight": "1", "group": "aamaadmiparty"}, {"source": "151", "target": "5", "id": 152, "weight": "1", "group": "aamaadmiparty"}, {"source": "151", "target": "166", "id": 153, "weight": "1", "group": "aamaadmiparty"}, {"source": "151", "target": "172", "id": 154, "weight": "1", "group": "aamaadmiparty"}, {"source": "0", "target": "7", "id": 155, "weight": "2", "group": "aamaadmiparty"}, {"source": "0", "target": "175", "id": 156, "weight": "2", "group": "aamaadmiparty"}, {"source": "0", "target": "36", "id": 157, "weight": "1", "group": "aamaadmiparty"}, {"source": "0", "target": "48", "id": 158, "weight": "1", "group": "aamaadmiparty"}, {"source": "0", "target": "23", "id": 159, "weight": "1", "group": "aamaadmiparty"}, {"source": "36", "target": "68", "id": 160, "weight": "1", "group": "aamaadmiparty"}, {"source": "36", "target": "53", "id": 161, "weight": "1", "group": "aamaadmiparty"}, {"source": "36", "target": "112", "id": 162, "weight": "1", "group": "aamaadmiparty"}, {"source": "36", "target": "135", "id": 163, "weight": "1", "group": "aamaadmiparty"}, {"source": "36", "target": "110", "id": 164, "weight": "1", "group": "aamaadmiparty"}, {"source": "36", "target": "105", "id": 165, "weight": "1", "group": "aamaadmiparty"}, {"source": "36", "target": "95", "id": 166, "weight": "1", "group": "aamaadmiparty"}, {"source": "36", "target": "154", "id": 167, "weight": "1", "group": "aamaadmiparty"}, {"source": "36", "target": "20", "id": 168, "weight": "1", "group": "aamaadmiparty"}, {"source": "36", "target": "126", "id": 169, "weight": "1", "group": "aamaadmiparty"}, {"source": "36", "target": "58", "id": 170, "weight": "1", "group": "aamaadmiparty"}, {"source": "36", "target": "119", "id": 171, "weight": "1", "group": "aamaadmiparty"}, {"source": "36", "target": "140", "id": 172, "weight": "1", "group": "aamaadmiparty"}, {"source": "36", "target": "34", "id": 173, "weight": "1", "group": "aamaadmiparty"}, {"source": "36", "target": "109", "id": 174, "weight": "1", "group": "aamaadmiparty"}, {"source": "36", "target": "18", "id": 175, "weight": "1", "group": "aamaadmiparty"}, {"source": "36", "target": "79", "id": 176, "weight": "1", "group": "aamaadmiparty"}, {"source": "36", "target": "163", "id": 177, "weight": "1", "group": "aamaadmiparty"}, {"source": "36", "target": "75", "id": 178, "weight": "1", "group": "aamaadmiparty"}, {"source": "36", "target": "159", "id": 179, "weight": "1", "group": "aamaadmiparty"}, {"source": "36", "target": "24", "id": 180, "weight": "1", "group": "aamaadmiparty"}, {"source": "36", "target": "134", "id": 181, "weight": "1", "group": "aamaadmiparty"}, {"source": "48", "target": "176", "id": 182, "weight": "1", "group": "aamaadmiparty"}, {"source": "48", "target": "35", "id": 183, "weight": "1", "group": "aamaadmiparty"}, {"source": "48", "target": "181", "id": 184, "weight": "2", "group": "aamaadmiparty"}, {"source": "23", "target": "84", "id": 185, "weight": "1", "group": "aamaadmiparty"}]}